findfile_path/__init__.py
findfile_path/__init__.py~
findfile_path/findfile_path.py
findfile_path/findfile_path.py~
findfile_path-0.2.post3.dist-info/LICENSE
findfile_path-0.2.post3.dist-info/METADATA
findfile_path-0.2.post3.dist-info/WHEEL
findfile_path-0.2.post3.dist-info/RECORD
