Metadata-Version: 2.1
Name: findfile_path
Version: 0.2.post3
Summary: Find file on path with optional extensions
Home-page: https://github.com/clearclaw/findfile_path
License: GPL-3.0-only
Keywords: find_file,search_file
Author: J C Lawrence
Author-email: claw@kanga.nu
Requires-Python: >=3.8,<4.0
Classifier: License :: OSI Approved :: GNU General Public License v3 (GPLv3)
Classifier: Programming Language :: Python :: 3
Classifier: Programming Language :: Python :: 3.8
Classifier: Programming Language :: Python :: 3.9
Classifier: Programming Language :: Python :: 3.10
Classifier: Programming Language :: Python :: 3.11
Classifier: Programming Language :: Python :: 3.12
Requires-Dist: logtool (>=0.4.post1)
Requires-Dist: path (>=16.14.0)
Project-URL: Repository, https://github.com/clearclaw/findfile_path
